cpq.cp37-win_amd64.pyd
hashbst.cp37-win_amd64.pyd
pybstree.cp37-win_amd64.pyd
pyhash.cp37-win_amd64.pyd
pystack.cp37-win_amd64.pyd
structpie/__init__.py
structpie-0.0.5.dist-info/LICENSE
structpie-0.0.5.dist-info/METADATA
structpie-0.0.5.dist-info/WHEEL
structpie-0.0.5.dist-info/top_level.txt
structpie-0.0.5.dist-info/RECORD
