Metadata-Version: 2.1
Name: structpie
Version: 0.0.5
Summary: A set of python modules for data structures written in C
Home-page: https://github.com/MNoorFawi/struct-pie
Author: Muhammad N. Fawi
Author-email: m.noor.fawi@gmail.com
License: MIT
Platform: UNKNOWN
Classifier: License :: OSI Approved :: MIT License
Classifier: Programming Language :: Python :: 3
Classifier: Programming Language :: Python :: 3.7
Classifier: Programming Language :: Python :: 3.8
Requires-Dist: cython
